fbmessenger/__init__.py
fbmessenger/api.py
fbmessenger/errors.py
fbmessenger/messenger.py
fbmessenger/models.py
simple_fbmessenger-0.1.0.dist-info/LICENSE
simple_fbmessenger-0.1.0.dist-info/METADATA
simple_fbmessenger-0.1.0.dist-info/WHEEL
simple_fbmessenger-0.1.0.dist-info/top_level.txt
simple_fbmessenger-0.1.0.dist-info/RECORD
